src/__init__.py
src/main.py
cse546backend-0.1.0.dist-info/entry_points.txt
cse546backend-0.1.0.dist-info/WHEEL
cse546backend-0.1.0.dist-info/METADATA
cse546backend-0.1.0.dist-info/RECORD
