Metadata-Version: 2.1
Name: cse546backend
Version: 0.1.0
Summary: 
Author: adityakrshnn
Author-email: adityakrshnn@gmail.com
Requires-Python: >=3.8,<4.0
Classifier: Programming Language :: Python :: 3
Classifier: Programming Language :: Python :: 3.10
Classifier: Programming Language :: Python :: 3.8
Classifier: Programming Language :: Python :: 3.9
Requires-Dist: fastapi[all] (>=0.74.1,<0.75.0)
